Metadata-Version: 2.1
Name: PassengerClassifier
Version: 0.0.1
Summary: BentoML generated model module
Home-page: https://github.com/atalaya-io/BentoML
License: UNKNOWN
Platform: UNKNOWN
